MANIFEST.in
README.rst
development.txt
requirements.txt
setup.cfg
setup.py
docs/Makefile
docs/make.bat
docs/source/api.rst
docs/source/cli.rst
docs/source/conf.py
docs/source/index.rst
keybone/__init__.py
keybone/conf.py
keybone/util.py
keybone/version.py
keybone.egg-info/PKG-INFO
keybone.egg-info/SOURCES.txt
keybone.egg-info/dependency_links.txt
keybone.egg-info/entry_points.txt
keybone.egg-info/not-zip-safe
keybone.egg-info/requires.txt
keybone.egg-info/top_level.txt
keybone/console/__init__.py
keybone/console/base.py
keybone/console/crypto.py
keybone/console/keys.py
keybone/console/main.py
keybone/console/operations.py
keybone/console/ui.py
keybone/console/util.py
keybone/console/parsers/__init__.py
keybone/console/parsers/backup.py
keybone/console/parsers/decrypt.py
keybone/console/parsers/delete_key.py
keybone/console/parsers/encrypt.py
keybone/console/parsers/generate_key.py
keybone/console/parsers/import_key.py
keybone/console/parsers/list_keys.py
keybone/console/parsers/quickstart.py
keybone/console/parsers/recover.py
keybone/console/parsers/show.py
keybone/console/parsers/show_passphrase.py
keybone/console/parsers/show_private.py
keybone/console/parsers/show_public.py
keybone/console/parsers/sign.py
keybone/console/parsers/verify.py
keybone/console/parsers/wipe.py
keybone/lib/__init__.py
keybone/lib/aes.py
keybone/lib/core.py