Metadata-Version: 1.0
Name: keybone
Version: 0.4.3
Summary: Create/Manage/List GPG Keys and Encrypt/Decrypt things with them
Home-page: https://github.com/gabrielfalcao/keybone
Author: Gabriel Falcao
Author-email: gabriel@nacaolivre.org
License: UNKNOWN
Platform: UNKNOWN
